{"comment":"Generated 2020/06/17. Please consult Terms-of-Use at https://mouselight.janelia.org when referencing this reconstruction.","neurons":[{"soma":{"x":7372.39235324999,"y":2289.559653,"z":8022.1541766875,"allenId":632},"idString":"AA0360","dendrite":[{"structureIdentifier":1,"parentNumber":-1,"x":7372.39235325,"y":2289.559653,"z":8022.1541766875,"radius":1,"allenId":632,"sampleNumber":1},{"structureIdentifier":3,"parentNumber":1,"x":7372.09271025,"y":2294.330024,"z":8022.1541766875,"radius":1,"allenId":632,"sampleNumber":2},{"structureIdentifier":3,"parentNumber":2,"x":7372.09271025,"y":2296.417061,"z":8022.1541766875,"radius":1,"allenId":632,"sampleNumber":3},{"structureIdentifier":3,"parentNumber":3,"x":7380.57013000001,"y":2309.68753025,"z":8028.478379875,"radius":1,"allenId":632,"sampleNumber":4},{"structureIdentifier":3,"parentNumber":4,"x":7374.89852500001,"y":2318.089781,"z":8028.7159705625,"radius":1,"allenId":632,"sampleNumber":5},{"structureIdentifier":3,"parentNumber":5,"x":7358.73071175,"y":2342.300796,"z":8046.691363375,"radius":1,"allenId":632,"sampleNumber":6},{"structureIdentifier":3,"parentNumber":6,"x":7298.820521,"y":2372.0977125,"z":8082.148608625,"radius":1,"allenId":10703,"sampleNumber":7},{"structureIdentifier":3,"parentNumber":7,"x":7277.82009250001,"y":2382.027277,"z":8096.548660625,"radius":1,"allenId":10703,"sampleNumber":8},{"structureIdentifier":3,"parentNumber":8,"x":7262.24985000001,"y":2369.0194645,"z":8101.60739625,"radius":1,"allenId":10703,"sampleNumber":9},{"structureIdentifier":3,"parentNumber":9,"x":7261.617205,"y":2365.4140265,"z":8103.29705525,"radius":1,"allenId":10703,"sampleNumber":10},{"structureIdentifier":3,"parentNumber":5,"x":7383.03097400001,"y":2332.59369975,"z":8027.9755461875,"radius":1,"allenId":632,"sampleNumber":11},{"structureIdentifier":3,"parentNumber":11,"x":7375.031468,"y":2332.5702525,"z":8023.6823864375,"radius":1,"allenId":632,"sampleNumber":12},{"structureIdentifier":3,"parentNumber":12,"x":7374.51145625001,"y":2374.460998,"z":8034.2937755625,"radius":1,"allenId":632,"sampleNumber":13},{"structureIdentifier":3,"parentNumber":13,"x":7366.66017525,"y":2401.47266625,"z":8032.0398830625,"radius":1,"allenId":10703,"sampleNumber":14},{"structureIdentifier":3,"parentNumber":14,"x":7375.71899050001,"y":2447.43353575,"z":8032.40047175,"radius":1,"allenId":10703,"sampleNumber":15},{"structureIdentifier":3,"parentNumber":15,"x":7387.00364375001,"y":2500.05081625,"z":8034.8995234375,"radius":1,"allenId":10703,"sampleNumber":16},{"structureIdentifier":3,"parentNumber":14,"x":7348.60553275001,"y":2433.04684975,"z":8037.431871625,"radius":1,"allenId":10703,"sampleNumber":17},{"structureIdentifier":3,"parentNumber":17,"x":7335.39039900001,"y":2475.79292775,"z":8049.417981,"radius":1,"allenId":10703,"sampleNumber":18},{"structureIdentifier":3,"parentNumber":18,"x":7331.25407175001,"y":2481.28522175,"z":8046.806714625,"radius":1,"allenId":10703,"sampleNumber":19},{"structureIdentifier":3,"parentNumber":19,"x":7320.55856825001,"y":2488.62502825,"z":8053.1532444375,"radius":1,"allenId":1009,"sampleNumber":20},{"structureIdentifier":3,"parentNumber":4,"x":7370.68772,"y":2315.191426,"z":8040.6299225625,"radius":1,"allenId":632,"sampleNumber":21},{"structureIdentifier":3,"parentNumber":21,"x":7360.28136050001,"y":2318.05472675,"z":8050.5987863125,"radius":1,"allenId":632,"sampleNumber":22},{"structureIdentifier":3,"parentNumber":22,"x":7358.46472375,"y":2336.23440825,"z":8073.6994385,"radius":1,"allenId":632,"sampleNumber":23},{"structureIdentifier":3,"parentNumber":23,"x":7350.72248275,"y":2353.24212325001,"z":8086.5926219375,"radius":1,"allenId":632,"sampleNumber":24},{"structureIdentifier":3,"parentNumber":24,"x":7350.41782375,"y":2376.1914525,"z":8110.277146,"radius":1,"allenId":632,"sampleNumber":25},{"structureIdentifier":3,"parentNumber":25,"x":7345.90253825001,"y":2408.02730325,"z":8143.90618525,"radius":1,"allenId":10703,"sampleNumber":26},{"structureIdentifier":3,"parentNumber":26,"x":7347.29282075001,"y":2432.15239575,"z":8165.8505349375,"radius":1,"allenId":10703,"sampleNumber":27},{"structureIdentifier":3,"parentNumber":21,"x":7356.312435,"y":2307.0117565,"z":8048.843868125,"radius":1,"allenId":632,"sampleNumber":28},{"structureIdentifier":3,"parentNumber":28,"x":7341.87887425,"y":2318.74605775,"z":8063.1103851875,"radius":1,"allenId":632,"sampleNumber":29},{"structureIdentifier":3,"parentNumber":29,"x":7314.28905000001,"y":2334.6797,"z":8091.5760685,"radius":1,"allenId":632,"sampleNumber":30},{"structureIdentifier":3,"parentNumber":30,"x":7291.48409200001,"y":2342.78122025,"z":8118.1436361875,"radius":1,"allenId":10703,"sampleNumber":31},{"structureIdentifier":3,"parentNumber":31,"x":7279.17988350001,"y":2355.46093075,"z":8137.4776461875,"radius":1,"allenId":10703,"sampleNumber":32},{"structureIdentifier":3,"parentNumber":32,"x":7263.50363425001,"y":2363.56251825,"z":8142.136628375,"radius":1,"allenId":1009,"sampleNumber":33},{"structureIdentifier":3,"parentNumber":33,"x":7264.76175375,"y":2371.6054545,"z":8150.0498431875,"radius":1,"allenId":1009,"sampleNumber":34},{"structureIdentifier":3,"parentNumber":1,"x":7367.29842025001,"y":2294.628172,"z":8027.0390156875,"radius":1,"allenId":632,"sampleNumber":35},{"structureIdentifier":3,"parentNumber":35,"x":7361.08600625,"y":2292.3104055,"z":8025.998976625,"radius":1,"allenId":632,"sampleNumber":36},{"structureIdentifier":3,"parentNumber":36,"x":7358.55074425001,"y":2290.5547085,"z":8035.896501625,"radius":1,"allenId":632,"sampleNumber":37},{"structureIdentifier":3,"parentNumber":37,"x":7349.69116725,"y":2285.5508425,"z":8038.6182258125,"radius":1,"allenId":632,"sampleNumber":38},{"structureIdentifier":3,"parentNumber":38,"x":7341.95729625001,"y":2278.843783,"z":8037.47248825,"radius":1,"allenId":632,"sampleNumber":39},{"structureIdentifier":3,"parentNumber":39,"x":7332.65252825001,"y":2283.1132475,"z":8041.6316853125,"radius":1,"allenId":632,"sampleNumber":40},{"structureIdentifier":3,"parentNumber":40,"x":7325.20709825,"y":2291.5702905,"z":8049.1120733125,"radius":1,"allenId":632,"sampleNumber":41},{"structureIdentifier":3,"parentNumber":41,"x":7304.63673675001,"y":2307.48436725,"z":8068.1747423125,"radius":1,"allenId":632,"sampleNumber":42},{"structureIdentifier":3,"parentNumber":42,"x":7277.96506475001,"y":2304.3477255,"z":8084.5616936875,"radius":1,"allenId":632,"sampleNumber":43},{"structureIdentifier":3,"parentNumber":43,"x":7267.80878175001,"y":2309.85161975,"z":8098.246249625,"radius":1,"allenId":632,"sampleNumber":44},{"structureIdentifier":3,"parentNumber":44,"x":7249.796631,"y":2302.14062325,"z":8103.949273875,"radius":1,"allenId":10703,"sampleNumber":45},{"structureIdentifier":3,"parentNumber":45,"x":7209.80053425001,"y":2302.96095675,"z":8127.7667671875,"radius":1,"allenId":1009,"sampleNumber":46},{"structureIdentifier":3,"parentNumber":46,"x":7210.00389975001,"y":2290.01555725,"z":8124.1981644375,"radius":1,"allenId":1009,"sampleNumber":47},{"structureIdentifier":3,"parentNumber":47,"x":7199.52345200001,"y":2275.07816,"z":8123.150286875,"radius":1,"allenId":1009,"sampleNumber":48},{"structureIdentifier":3,"parentNumber":39,"x":7330.74996250001,"y":2274.94145425,"z":8041.513533125,"radius":1,"allenId":632,"sampleNumber":49},{"structureIdentifier":3,"parentNumber":49,"x":7318.42583125,"y":2261.722609,"z":8058.2568770625,"radius":1,"allenId":632,"sampleNumber":50},{"structureIdentifier":3,"parentNumber":50,"x":7304.26145575001,"y":2251.38666125,"z":8072.775437,"radius":1,"allenId":632,"sampleNumber":51},{"structureIdentifier":3,"parentNumber":51,"x":7288.28115000001,"y":2229.5156705,"z":8081.07819775,"radius":1,"allenId":10703,"sampleNumber":52},{"structureIdentifier":3,"parentNumber":52,"x":7275.08221425001,"y":2200.66009100001,"z":8097.88279725,"radius":1,"allenId":10703,"sampleNumber":53},{"structureIdentifier":3,"parentNumber":53,"x":7267.32036100001,"y":2179.218742,"z":8120.14661575,"radius":1,"allenId":10703,"sampleNumber":54},{"structureIdentifier":3,"parentNumber":50,"x":7296.20679075,"y":2246.25001125001,"z":8066.964672,"radius":1,"allenId":632,"sampleNumber":55},{"structureIdentifier":3,"parentNumber":55,"x":7284.47248475,"y":2237.132879,"z":8075.6416150625,"radius":1,"allenId":10703,"sampleNumber":56},{"structureIdentifier":3,"parentNumber":56,"x":7267.61304025001,"y":2218.81641425,"z":8102.15436975,"radius":1,"allenId":10703,"sampleNumber":57},{"structureIdentifier":3,"parentNumber":57,"x":7269.34744325001,"y":2198.890565,"z":8108.62896725,"radius":1,"allenId":10703,"sampleNumber":58},{"structureIdentifier":3,"parentNumber":58,"x":7263.5309825,"y":2195.26175725,"z":8123.5595846875,"radius":1,"allenId":10703,"sampleNumber":59},{"structureIdentifier":3,"parentNumber":59,"x":7268.11317025001,"y":2194.128929,"z":8127.23238425,"radius":1,"allenId":10703,"sampleNumber":60},{"structureIdentifier":3,"parentNumber":60,"x":7263.08959475001,"y":2185.71877325,"z":8127.1844064375,"radius":1,"allenId":10703,"sampleNumber":61},{"structureIdentifier":3,"parentNumber":56,"x":7250.93368275001,"y":2207.42575075,"z":8089.64659725,"radius":1,"allenId":10703,"sampleNumber":62},{"structureIdentifier":3,"parentNumber":62,"x":7235.09000475,"y":2197.47651975,"z":8096.3582254375,"radius":1,"allenId":10703,"sampleNumber":63},{"structureIdentifier":3,"parentNumber":63,"x":7227.22656000001,"y":2181.43746225,"z":8099.5850445625,"radius":1,"allenId":10703,"sampleNumber":64},{"structureIdentifier":3,"parentNumber":64,"x":7224.43387075,"y":2171.80074625,"z":8099.3028365,"radius":1,"allenId":822,"sampleNumber":65},{"structureIdentifier":3,"parentNumber":65,"x":7237.14861800001,"y":2169.851587,"z":8105.8153986875,"radius":1,"allenId":502,"sampleNumber":66},{"structureIdentifier":3,"parentNumber":66,"x":7238.93769800001,"y":2165.80082,"z":8113.8386526875,"radius":1,"allenId":502,"sampleNumber":67},{"structureIdentifier":3,"parentNumber":49,"x":7313.44897375001,"y":2282.04298575,"z":8051.2491889375,"radius":1,"allenId":632,"sampleNumber":68},{"structureIdentifier":3,"parentNumber":68,"x":7294.97262075001,"y":2282.03908925,"z":8056.9834148125,"radius":1,"allenId":632,"sampleNumber":69},{"structureIdentifier":3,"parentNumber":69,"x":7268.30076425,"y":2284.6367315,"z":8067.0183858125,"radius":1,"allenId":632,"sampleNumber":70},{"structureIdentifier":3,"parentNumber":70,"x":7233.17587825001,"y":2280.9999535,"z":8067.8153365625,"radius":1,"allenId":10703,"sampleNumber":71},{"structureIdentifier":3,"parentNumber":71,"x":7210.75387375,"y":2292.69527225,"z":8067.66000325,"radius":1,"allenId":10703,"sampleNumber":72},{"structureIdentifier":3,"parentNumber":72,"x":7187.17564775,"y":2305.46870775001,"z":8046.8016304375,"radius":1,"allenId":10703,"sampleNumber":73},{"structureIdentifier":3,"parentNumber":73,"x":7161.51966125,"y":2335.183588,"z":8039.2393755625,"radius":1,"allenId":1009,"sampleNumber":74},{"structureIdentifier":3,"parentNumber":69,"x":7282.48060425001,"y":2277.37890700001,"z":8067.6633146875,"radius":1,"allenId":632,"sampleNumber":75},{"structureIdentifier":3,"parentNumber":75,"x":7273.1172335,"y":2274.839867,"z":8088.726720125,"radius":1,"allenId":632,"sampleNumber":76},{"structureIdentifier":3,"parentNumber":76,"x":7258.726305,"y":2252.71491525,"z":8099.27166775,"radius":1,"allenId":10703,"sampleNumber":77},{"structureIdentifier":3,"parentNumber":77,"x":7259.24239350001,"y":2243.61330725,"z":8108.8312486875,"radius":1,"allenId":10703,"sampleNumber":78},{"structureIdentifier":3,"parentNumber":78,"x":7252.320391,"y":2225.2617465,"z":8126.454900125,"radius":1,"allenId":10703,"sampleNumber":79},{"structureIdentifier":3,"parentNumber":79,"x":7256.7576295,"y":2218.7655535,"z":8129.3448131875,"radius":1,"allenId":10703,"sampleNumber":80},{"structureIdentifier":3,"parentNumber":80,"x":7259.398319,"y":2201.95318725,"z":8127.9267931875,"radius":1,"allenId":10703,"sampleNumber":81},{"structureIdentifier":3,"parentNumber":75,"x":7245.22253375001,"y":2260.5780715,"z":8088.5184006875,"radius":1,"allenId":10703,"sampleNumber":82},{"structureIdentifier":3,"parentNumber":82,"x":7229.74208900001,"y":2260.96871325,"z":8094.4285146875,"radius":1,"allenId":10703,"sampleNumber":83},{"structureIdentifier":3,"parentNumber":83,"x":7215.50411975001,"y":2259.84376,"z":8107.181638,"radius":1,"allenId":10703,"sampleNumber":84},{"structureIdentifier":3,"parentNumber":84,"x":7193.59756025001,"y":2263.04687775,"z":8119.966923625,"radius":1,"allenId":1009,"sampleNumber":85},{"structureIdentifier":3,"parentNumber":85,"x":7193.48039125001,"y":2252.41021725,"z":8121.6589694375,"radius":1,"allenId":1009,"sampleNumber":86}],"label":{"fluorophore":"tdTomato","virus":"AAV 2/1 Cre + FP"},"axon":[{"structureIdentifier":1,"parentNumber":-1,"x":7372.39235324999,"y":2289.559653,"z":8022.1541766875,"radius":1,"allenId":632,"sampleNumber":1},{"structureIdentifier":2,"parentNumber":1,"x":7373.29128325,"y":2288.665209,"z":8024.1081126875,"radius":1,"allenId":632,"sampleNumber":2},{"structureIdentifier":2,"parentNumber":2,"x":7382.36454675,"y":2285.351783,"z":8021.9069408125,"radius":1,"allenId":632,"sampleNumber":3},{"structureIdentifier":2,"parentNumber":3,"x":7396.6174545,"y":2278.66009675,"z":8007.8642700625,"radius":1,"allenId":632,"sampleNumber":4},{"structureIdentifier":2,"parentNumber":4,"x":7441.90629849999,"y":2265.39845375,"z":7976.1161274375,"radius":1,"allenId":632,"sampleNumber":5},{"structureIdentifier":2,"parentNumber":5,"x":7489.42568575,"y":2292.89458399999,"z":7935.5557201875,"radius":1,"allenId":632,"sampleNumber":6},{"structureIdentifier":2,"parentNumber":6,"x":7499.69168875,"y":2300.39849425,"z":7930.6144005625,"radius":1,"allenId":632,"sampleNumber":7},{"structureIdentifier":2,"parentNumber":7,"x":7525.25414325,"y":2308.4569825,"z":7954.060447,"radius":1,"allenId":632,"sampleNumber":8},{"structureIdentifier":2,"parentNumber":8,"x":7541.5158825,"y":2307.984412,"z":7966.361467,"radius":1,"allenId":632,"sampleNumber":9},{"structureIdentifier":2,"parentNumber":9,"x":7561.92558675,"y":2315.6835785,"z":7987.3661328125,"radius":1,"allenId":632,"sampleNumber":10},{"structureIdentifier":2,"parentNumber":10,"x":7583.73849725,"y":2324.539106,"z":8001.55070675,"radius":1,"allenId":632,"sampleNumber":11},{"structureIdentifier":2,"parentNumber":11,"x":7604.44560399999,"y":2341.94926325,"z":8016.9990886875,"radius":1,"allenId":632,"sampleNumber":12},{"structureIdentifier":2,"parentNumber":12,"x":7651.093822,"y":2372.71481475,"z":8051.27548125,"radius":1,"allenId":632,"sampleNumber":13},{"structureIdentifier":2,"parentNumber":13,"x":7665.999815,"y":2368.050848,"z":8055.558775375,"radius":1,"allenId":632,"sampleNumber":14},{"structureIdentifier":2,"parentNumber":14,"x":7680.24607075,"y":2378.72261999999,"z":8066.6766469375,"radius":1,"allenId":632,"sampleNumber":15},{"structureIdentifier":2,"parentNumber":15,"x":7688.41381499999,"y":2380.03130549999,"z":8077.611291375,"radius":1,"allenId":632,"sampleNumber":16},{"structureIdentifier":2,"parentNumber":16,"x":7706.46489575,"y":2383.9882875,"z":8090.7468865625,"radius":1,"allenId":632,"sampleNumber":17},{"structureIdentifier":2,"parentNumber":17,"x":7749.195175,"y":2396.17970874999,"z":8110.6902665625,"radius":1,"allenId":632,"sampleNumber":18},{"structureIdentifier":2,"parentNumber":18,"x":7757.00392224999,"y":2420.85937,"z":8100.23427025,"radius":1,"allenId":632,"sampleNumber":19},{"structureIdentifier":2,"parentNumber":19,"x":7774.75402825,"y":2436.73435625,"z":8096.5029639375,"radius":1,"allenId":632,"sampleNumber":20},{"structureIdentifier":2,"parentNumber":20,"x":7799.94544499999,"y":2469.92180924999,"z":8086.011843625,"radius":1,"allenId":632,"sampleNumber":21},{"structureIdentifier":2,"parentNumber":21,"x":7824.69560349999,"y":2501.5898405,"z":8091.2746263125,"radius":1,"allenId":632,"sampleNumber":22},{"structureIdentifier":2,"parentNumber":22,"x":7818.91783325,"y":2475.730482,"z":8111.890471125,"radius":1,"allenId":632,"sampleNumber":23},{"structureIdentifier":2,"parentNumber":23,"x":7816.98806325,"y":2465.85942725,"z":8113.1140415625,"radius":1,"allenId":632,"sampleNumber":24},{"structureIdentifier":2,"parentNumber":7,"x":7504.70324849999,"y":2311.05463599999,"z":7921.574114125,"radius":1,"allenId":632,"sampleNumber":25},{"structureIdentifier":2,"parentNumber":25,"x":7540.01929025,"y":2317.390679,"z":7924.7038795625,"radius":1,"allenId":632,"sampleNumber":26},{"structureIdentifier":2,"parentNumber":26,"x":7569.22652549999,"y":2323.75397825,"z":7929.6066475625,"radius":1,"allenId":632,"sampleNumber":27},{"structureIdentifier":2,"parentNumber":27,"x":7609.195131,"y":2317.906281,"z":7941.685753875,"radius":1,"allenId":632,"sampleNumber":28},{"structureIdentifier":2,"parentNumber":28,"x":7627.51171725,"y":2330.26558575,"z":7949.5692096875,"radius":1,"allenId":632,"sampleNumber":29},{"structureIdentifier":2,"parentNumber":29,"x":7650.0546685,"y":2325.332067,"z":7945.9318195,"radius":1,"allenId":632,"sampleNumber":30},{"structureIdentifier":2,"parentNumber":30,"x":7674.539212,"y":2333.98435925,"z":7946.630820875,"radius":1,"allenId":632,"sampleNumber":31},{"structureIdentifier":2,"parentNumber":31,"x":7713.42203099999,"y":2364.70313725,"z":7941.87326325,"radius":1,"allenId":632,"sampleNumber":32},{"structureIdentifier":2,"parentNumber":32,"x":7722.0079195,"y":2373.94524825,"z":7936.0048736875,"radius":1,"allenId":632,"sampleNumber":33},{"structureIdentifier":2,"parentNumber":33,"x":7726.9999565,"y":2365.00397375,"z":7926.21679075,"radius":1,"allenId":632,"sampleNumber":34},{"structureIdentifier":2,"parentNumber":34,"x":7740.99601925,"y":2372.99604524999,"z":7918.671746875,"radius":1,"allenId":632,"sampleNumber":35},{"structureIdentifier":2,"parentNumber":35,"x":7757.1092675,"y":2365.82420549999,"z":7895.4015545625,"radius":1,"allenId":632,"sampleNumber":36},{"structureIdentifier":2,"parentNumber":36,"x":7764.66801675,"y":2375.753843,"z":7887.677648375,"radius":1,"allenId":632,"sampleNumber":37},{"structureIdentifier":2,"parentNumber":37,"x":7743.3982885,"y":2366.15627775,"z":7899.5146220625,"radius":1,"allenId":632,"sampleNumber":38},{"structureIdentifier":2,"parentNumber":38,"x":7720.90213624999,"y":2358.49605125,"z":7902.0305013125,"radius":1,"allenId":632,"sampleNumber":39},{"structureIdentifier":2,"parentNumber":39,"x":7718.28494025,"y":2358.03907525,"z":7909.9034893125,"radius":1,"allenId":632,"sampleNumber":40},{"structureIdentifier":2,"parentNumber":25,"x":7506.4531175,"y":2314.02738299999,"z":7906.923888125,"radius":1,"allenId":632,"sampleNumber":41},{"structureIdentifier":2,"parentNumber":41,"x":7551.3435265,"y":2351.7069815,"z":7873.871180375,"radius":1,"allenId":632,"sampleNumber":42},{"structureIdentifier":2,"parentNumber":42,"x":7589.83962474999,"y":2368.87496474999,"z":7860.0694058125,"radius":1,"allenId":632,"sampleNumber":43},{"structureIdentifier":2,"parentNumber":43,"x":7618.195448,"y":2386.84763624999,"z":7845.9578975625,"radius":1,"allenId":632,"sampleNumber":44},{"structureIdentifier":2,"parentNumber":44,"x":7627.89070199999,"y":2394.0859335,"z":7827.8340095,"radius":1,"allenId":632,"sampleNumber":45},{"structureIdentifier":2,"parentNumber":45,"x":7647.66779875,"y":2418.457036,"z":7816.455015125,"radius":1,"allenId":632,"sampleNumber":46},{"structureIdentifier":2,"parentNumber":46,"x":7650.07430774999,"y":2420.222632,"z":7806.677703125,"radius":1,"allenId":632,"sampleNumber":47},{"structureIdentifier":2,"parentNumber":47,"x":7658.12133025,"y":2423.695274,"z":7787.1122029375,"radius":1,"allenId":632,"sampleNumber":48},{"structureIdentifier":2,"parentNumber":48,"x":7667.26184024999,"y":2431.53911149999,"z":7775.8722613125,"radius":1,"allenId":632,"sampleNumber":49},{"structureIdentifier":2,"parentNumber":42,"x":7564.73809925,"y":2357.50777675,"z":7850.63079,"radius":1,"allenId":632,"sampleNumber":50},{"structureIdentifier":2,"parentNumber":50,"x":7565.21511875,"y":2364.06247049999,"z":7832.1101308125,"radius":1,"allenId":632,"sampleNumber":51},{"structureIdentifier":2,"parentNumber":51,"x":7565.2971325,"y":2363.51946525,"z":7794.3289638125,"radius":1,"allenId":632,"sampleNumber":52},{"structureIdentifier":2,"parentNumber":52,"x":7545.4298615,"y":2354.08596149999,"z":7762.4092830625,"radius":1,"allenId":632,"sampleNumber":53},{"structureIdentifier":2,"parentNumber":53,"x":7528.60520275,"y":2337.60552025,"z":7742.3195226875,"radius":1,"allenId":632,"sampleNumber":54},{"structureIdentifier":2,"parentNumber":54,"x":7508.0622535,"y":2328.10943225,"z":7730.990086375,"radius":1,"allenId":632,"sampleNumber":55},{"structureIdentifier":2,"parentNumber":55,"x":7460.8828695,"y":2306.417921,"z":7711.9504293125,"radius":1,"allenId":632,"sampleNumber":56},{"structureIdentifier":2,"parentNumber":56,"x":7456.0388635,"y":2309.90232525,"z":7673.4519974375,"radius":1,"allenId":632,"sampleNumber":57},{"structureIdentifier":2,"parentNumber":57,"x":7437.5077705,"y":2327.79685875,"z":7655.4543029375,"radius":1,"allenId":632,"sampleNumber":58},{"structureIdentifier":2,"parentNumber":58,"x":7433.8827915,"y":2333.23835375,"z":7641.8406739375,"radius":1,"allenId":632,"sampleNumber":59},{"structureIdentifier":2,"parentNumber":52,"x":7591.83987124999,"y":2377.33594075,"z":7753.14655375,"radius":1,"allenId":632,"sampleNumber":60},{"structureIdentifier":2,"parentNumber":60,"x":7599.992205,"y":2379.56245925,"z":7722.3010025,"radius":1,"allenId":632,"sampleNumber":61},{"structureIdentifier":2,"parentNumber":61,"x":7619.0313185,"y":2402.33588424999,"z":7704.033180625,"radius":1,"allenId":632,"sampleNumber":62},{"structureIdentifier":2,"parentNumber":62,"x":7631.75363774999,"y":2422.27728625,"z":7681.492234625,"radius":1,"allenId":632,"sampleNumber":63},{"structureIdentifier":2,"parentNumber":63,"x":7635.32419074999,"y":2428.03512625,"z":7674.769377625,"radius":1,"allenId":632,"sampleNumber":64},{"structureIdentifier":2,"parentNumber":64,"x":7653.00008899999,"y":2446.05855875,"z":7652.9675554375,"radius":1,"allenId":632,"sampleNumber":65},{"structureIdentifier":2,"parentNumber":65,"x":7648.89872299999,"y":2448.49993775,"z":7633.3933724375,"radius":1,"allenId":632,"sampleNumber":66},{"structureIdentifier":2,"parentNumber":66,"x":7660.96847549999,"y":2453.7266255,"z":7606.800670375,"radius":1,"allenId":10704,"sampleNumber":67},{"structureIdentifier":2,"parentNumber":67,"x":7655.32020049999,"y":2461.136707,"z":7567.9588385,"radius":1,"allenId":10704,"sampleNumber":68},{"structureIdentifier":2,"parentNumber":68,"x":7635.18766749999,"y":2468.25390375,"z":7529.962884375,"radius":1,"allenId":10704,"sampleNumber":69},{"structureIdentifier":2,"parentNumber":69,"x":7639.75396325,"y":2489.16015449999,"z":7498.29507225,"radius":1,"allenId":10704,"sampleNumber":70},{"structureIdentifier":2,"parentNumber":70,"x":7632.20306,"y":2512.50397049999,"z":7430.0517906875,"radius":1,"allenId":10704,"sampleNumber":71},{"structureIdentifier":2,"parentNumber":71,"x":7644.2106695,"y":2575.76176325,"z":7389.7355818125,"radius":1,"allenId":463,"sampleNumber":72},{"structureIdentifier":2,"parentNumber":72,"x":7633.56629274999,"y":2603.20314475,"z":7365.2685758125,"radius":1,"allenId":463,"sampleNumber":73},{"structureIdentifier":2,"parentNumber":73,"x":7643.7889575,"y":2642.51957425,"z":7338.0830419375,"radius":1,"allenId":463,"sampleNumber":74},{"structureIdentifier":2,"parentNumber":74,"x":7649.96463525,"y":2645.80082275,"z":7323.59980775,"radius":1,"allenId":463,"sampleNumber":75},{"structureIdentifier":2,"parentNumber":75,"x":7657.210655,"y":2668.27345525,"z":7286.27541125,"radius":1,"allenId":463,"sampleNumber":76},{"structureIdentifier":2,"parentNumber":76,"x":7665.62880974999,"y":2670.99604999999,"z":7272.7685338125,"radius":1,"allenId":463,"sampleNumber":77},{"structureIdentifier":2,"parentNumber":77,"x":7670.36340575,"y":2670.359428,"z":7261.0907138125,"radius":1,"allenId":463,"sampleNumber":78},{"structureIdentifier":2,"parentNumber":78,"x":7674.61326825,"y":2704.92191824999,"z":7218.3956920625,"radius":1,"allenId":463,"sampleNumber":79},{"structureIdentifier":2,"parentNumber":79,"x":7702.242031,"y":2706.09759575,"z":7159.006010375,"radius":1,"allenId":463,"sampleNumber":80},{"structureIdentifier":2,"parentNumber":80,"x":7706.00408225,"y":2694.574244,"z":7153.792821875,"radius":1,"allenId":463,"sampleNumber":81},{"structureIdentifier":2,"parentNumber":80,"x":7698.12509849999,"y":2699.07819774999,"z":7127.7765781875,"radius":1,"allenId":463,"sampleNumber":82},{"structureIdentifier":2,"parentNumber":82,"x":7788.79702299999,"y":2693.66408625,"z":7018.9443549375,"radius":1,"allenId":463,"sampleNumber":83},{"structureIdentifier":2,"parentNumber":83,"x":7788.46076099999,"y":2680.41795924999,"z":7003.7459195,"radius":1,"allenId":463,"sampleNumber":84},{"structureIdentifier":2,"parentNumber":84,"x":7807.36356524999,"y":2672.230409,"z":6979.7568263125,"radius":1,"allenId":463,"sampleNumber":85},{"structureIdentifier":2,"parentNumber":85,"x":7819.9919655,"y":2664.02338925,"z":6962.070403625,"radius":1,"allenId":463,"sampleNumber":86},{"structureIdentifier":2,"parentNumber":86,"x":7847.72281374999,"y":2638.6992315,"z":6943.296961,"radius":1,"allenId":463,"sampleNumber":87},{"structureIdentifier":2,"parentNumber":87,"x":7858.57436274999,"y":2640.0117555,"z":6942.8056313125,"radius":1,"allenId":463,"sampleNumber":88},{"structureIdentifier":2,"parentNumber":88,"x":7853.31656275,"y":2634.1132845,"z":6944.8702393125,"radius":1,"allenId":463,"sampleNumber":89},{"structureIdentifier":2,"parentNumber":88,"x":7913.34741224999,"y":2622.37893525,"z":6907.7958659375,"radius":1,"allenId":463,"sampleNumber":90},{"structureIdentifier":2,"parentNumber":90,"x":7922.710972,"y":2631.96874875,"z":6891.75784475,"radius":1,"allenId":463,"sampleNumber":91},{"structureIdentifier":2,"parentNumber":90,"x":7940.945588,"y":2608.66402325,"z":6902.8798391875,"radius":1,"allenId":463,"sampleNumber":92},{"structureIdentifier":2,"parentNumber":92,"x":7991.1950505,"y":2571.43356899999,"z":6908.7497685,"radius":1,"allenId":463,"sampleNumber":93},{"structureIdentifier":2,"parentNumber":93,"x":7985.10152549999,"y":2571.437499,"z":6912.3924085,"radius":1,"allenId":463,"sampleNumber":94},{"structureIdentifier":2,"parentNumber":93,"x":8041.28151849999,"y":2543.9961575,"z":6901.773539,"radius":1,"allenId":463,"sampleNumber":95},{"structureIdentifier":2,"parentNumber":95,"x":8088.98855875,"y":2526.043021,"z":6938.20719375,"radius":1,"allenId":463,"sampleNumber":96},{"structureIdentifier":2,"parentNumber":96,"x":8109.289349,"y":2496.71095125,"z":6961.0809364375,"radius":1,"allenId":463,"sampleNumber":97},{"structureIdentifier":2,"parentNumber":97,"x":8143.16017725,"y":2482.0234495,"z":6987.3506198125,"radius":1,"allenId":463,"sampleNumber":98},{"structureIdentifier":2,"parentNumber":98,"x":8184.36319424999,"y":2457.05475575,"z":7021.2937215625,"radius":1,"allenId":463,"sampleNumber":99},{"structureIdentifier":2,"parentNumber":99,"x":8196.58614299999,"y":2443.41798775,"z":7029.410265625,"radius":1,"allenId":463,"sampleNumber":100},{"structureIdentifier":2,"parentNumber":100,"x":8231.42185299999,"y":2438.831961,"z":7056.98437575,"radius":1,"allenId":463,"sampleNumber":101},{"structureIdentifier":2,"parentNumber":101,"x":8240.3359685,"y":2441.9647725,"z":7054.902132,"radius":1,"allenId":463,"sampleNumber":102},{"structureIdentifier":2,"parentNumber":102,"x":8234.421795,"y":2441.800777,"z":7055.96876775,"radius":1,"allenId":463,"sampleNumber":103},{"structureIdentifier":2,"parentNumber":102,"x":8267.007564,"y":2451.0663955,"z":7061.7841003125,"radius":1,"allenId":463,"sampleNumber":104},{"structureIdentifier":2,"parentNumber":104,"x":8281.952964,"y":2448.742232,"z":7064.337913375,"radius":1,"allenId":463,"sampleNumber":105},{"structureIdentifier":2,"parentNumber":105,"x":8306.55474149999,"y":2450.77336699999,"z":7061.482644875,"radius":1,"allenId":463,"sampleNumber":106},{"structureIdentifier":2,"parentNumber":106,"x":8341.49609674999,"y":2434.8008055,"z":7091.7022486875,"radius":1,"allenId":463,"sampleNumber":107},{"structureIdentifier":2,"parentNumber":107,"x":8370.42573475,"y":2435.67975625,"z":7123.6515265625,"radius":1,"allenId":463,"sampleNumber":108},{"structureIdentifier":2,"parentNumber":108,"x":8406.18355375,"y":2442.4061945,"z":7137.9141065,"radius":1,"allenId":463,"sampleNumber":109},{"structureIdentifier":2,"parentNumber":109,"x":8411.79308475,"y":2440.0156235,"z":7143.3084195,"radius":1,"allenId":463,"sampleNumber":110},{"structureIdentifier":2,"parentNumber":77,"x":7657.68358324999,"y":2673.15622075,"z":7269.9011494375,"radius":1,"allenId":463,"sampleNumber":111}],"sample":{"date":"2017-09-19T19:27:58.000Z","strain":"C57BL/6J"},"DOI":"10.25378/janelia.7613861","allenInformation":[{"acronym":"CA3","name":"Field CA3","graphOrder":463,"allenId":463,"colorHex":"7ED04B","safeName":"Field CA3","structureIdPath":"/997/8/567/688/695/1089/1080/375/463/"},{"acronym":"SUB","name":"Subiculum","graphOrder":531,"allenId":502,"colorHex":"4FC244","safeName":"Subiculum","structureIdPath":"/997/8/567/688/695/1089/822/502/"},{"acronym":"DG-sg","name":"Dentate gyrus, granule cell layer","graphOrder":472,"allenId":632,"colorHex":"66A83D","safeName":"Dentate gyrus granule cell layer","structureIdPath":"/997/8/567/688/695/1089/1080/726/632/"},{"acronym":"RHP","name":"Retrohippocampal region","graphOrder":488,"allenId":822,"colorHex":"32B825","safeName":"Retrohippocampal region","structureIdPath":"/997/8/567/688/695/1089/822/"},{"acronym":"fiber tracts","name":"fiber tracts","graphOrder":1061,"allenId":1009,"colorHex":"CCCCCC","safeName":"fiber tracts","structureIdPath":"/997/1009/"},{"acronym":"DG-mo","name":"Dentate gyrus, molecular layer","graphOrder":470,"allenId":10703,"colorHex":"7ED04B","safeName":"Dentate gyrus molecular layer","structureIdPath":"/997/8/567/688/695/1089/1080/726/10703/"},{"acronym":"DG-po","name":"Dentate gyrus, polymorph layer","graphOrder":471,"allenId":10704,"colorHex":"7ED04B","safeName":"Dentate gyrus polymorph layer","structureIdPath":"/997/8/567/688/695/1089/1080/726/10704/"}]}]}